<?xml version="1.0" encoding="utf-8"?>
<Catalog>
    <CAttachMethodPattern id="AMPatternDrunkenMissileVolleyNod">
        <Keyword value="Weapon"/>
        <Driver value="NodHailstormMissilePodsLaunchMissile"/>
    </CAttachMethodPattern>
    <CAttachMethodPattern id="AMPatternLaserCannon">
        <Keyword value="Weapon"/>
        <Driver value="NodLaserCannonDamage"/>
    </CAttachMethodPattern>
    <CAttachMethodPattern id="NodBikeRocketUp">
        <Keyword value="Weapon"/>
        <Driver value="NodBikeRocketUpLaunchMissile"/>
    </CAttachMethodPattern>
    <CAttachMethodPattern id="NodMCVRocket">
        <Keyword value="Weapon"/>
        <Driver value="NodMCVRocketLaunchMissile"/>
    </CAttachMethodPattern>
    <CAttachMethodPattern id="NodBikeRocketNodCC3">
        <Keyword value="Weapon"/>
        <Driver value="NodBikeRocketLaunchMissileCC3"/>
    </CAttachMethodPattern>
    <CAttachMethodPattern id="CabalLeviathanLaunchMissile">
        <Keyword value="Weapon"/>
        <Driver value="CabalLeviathanLaunchMissile"/>
    </CAttachMethodPattern>
    <CAttachMethodPattern id="NodStealthTankRocket">
        <Keyword value="Weapon"/>
        <Driver value="NodStealthRocketLaunchMissile"/>
    </CAttachMethodPattern>
    <CAttachMethodPattern id="NodStealthTankRocketUP">
        <Keyword value="Weapon"/>
        <Driver value="NodStealthRocketLaunchMissileUP"/>
    </CAttachMethodPattern>
    <CAttachMethodPattern id="RaiderWeaponNod">
        <Keyword value="Weapon"/>
        <Driver value="NodRaiderDamage"/>
    </CAttachMethodPattern>
    <CAttachMethodPattern id="NodBikeRocketNod">
        <Keyword value="Weapon"/>
        <Driver value="NodBikeRocketLaunchMissile"/>
    </CAttachMethodPattern>
    <CAttachMethodFilter id="Weapon0203">
        <Keys Keyword="Weapon" Index="2"/>
        <Keys Keyword="Weapon" Index="3"/>
        <Logic value="OR"/>
    </CAttachMethodFilter>
    <CAttachMethodFilter id="Weapon010203">
        <Keys Keyword="Weapon" Index="1"/>
        <Keys Keyword="Weapon" Index="2"/>
        <Keys Keyword="Weapon" Index="3"/>
        <Logic value="OR"/>
    </CAttachMethodFilter>
</Catalog>
